{
    "m_Version": 12,
    "DisplayName": "Range Rover Sport",
    "Icon": "Deliver",
    "Color": "FBFCFEFF",
    "InitStockPercent": 75.0,
    "IsExchange": 0,
    "Items": [
        {
            "ClassName": "CrSk_Land_Rover_RR_Sport_12",
            "MaxPriceThreshold": 1200000.0,
            "MinPriceThreshold": 1200000.0,
            "SellPricePercent": -1,
            "MaxStockThreshold": 1,
            "MinStockThreshold": 1,
            "QuantityPercent": -1,
            "SpawnAttachments": [],
            "Variants": []
        },
        {
            "ClassName": "CrSk_Land_Rover_RR_Sport_12_Black",
            "MaxPriceThreshold": 1200000.0,
            "MinPriceThreshold": 1200000.0,
            "SellPricePercent": -1,
            "MaxStockThreshold": 1,
            "MinStockThreshold": 1,
            "QuantityPercent": -1,
            "SpawnAttachments": [],
            "Variants": []
        }
    ]
}